Metadata-Version: 2.1
Name: megnet
Version: 1.3.2
Summary: MatErials Graph Networks for machine learning of molecules and crystals.
Download-URL: https://github.com/materialsvirtuallab/megnet
Author: Chi Chen
Author-email: chc273@eng.ucsd.edu
License: BSD
Keywords: materials,science,machine,learning,deep,graph,networks,neural
Classifier: Programming Language :: Python :: 3
Classifier: Programming Language :: Python :: 3.7
Classifier: Programming Language :: Python :: 3.8
Classifier: Programming Language :: Python :: 3.9
Classifier: Programming Language :: Python :: 3.10
Classifier: Development Status :: 4 - Beta
Classifier: Intended Audience :: Science/Research
Classifier: License :: OSI Approved :: BSD License
Classifier: Operating System :: OS Independent
Classifier: Topic :: Scientific/Engineering :: Information Analysis
Classifier: Topic :: Scientific/Engineering :: Physics
Classifier: Topic :: Scientific/Engineering :: Chemistry
Classifier: Topic :: Software Development :: Libraries :: Python Modules
License-File: LICENSE.md
Requires-Dist: numpy
Requires-Dist: scikit-learn
Requires-Dist: pymatgen (>=2019.10.4)
Requires-Dist: monty
Requires-Dist: tqdm
Provides-Extra: model_saving
Requires-Dist: h5py ; extra == 'model_saving'
Provides-Extra: molecules
Requires-Dist: openbabel ; extra == 'molecules'
Requires-Dist: rdkit ; extra == 'molecules'
Provides-Extra: tensorflow
Requires-Dist: tensorflow (>=2.1) ; extra == 'tensorflow'
Provides-Extra: tensorflow_with_gpu
Requires-Dist: tensorflow-gpu (>=2.1) ; extra == 'tensorflow_with_gpu'
